LICENSE
README.md
pyproject.toml
setup.cfg
./EmonUtils/__init__.py
./EmonUtils/__main__.py
./EmonUtils/DBIO/__init__.py
./EmonUtils/DBIO/dbio.py
./EmonUtils/EmonIO/__init__.py
./EmonUtils/EmonIO/emonio.py
./EmonUtils/setup/__init__.py
./EmonUtils/setup/generate_config.py
./EmonUtils/setup/generate_schema.py
emon_utils.egg-info/PKG-INFO
emon_utils.egg-info/SOURCES.txt
emon_utils.egg-info/dependency_links.txt
emon_utils.egg-info/requires.txt
emon_utils.egg-info/top_level.txt