Metadata-Version: 2.1
Name: emon-utils
Version: 0.4
Summary: A simple integration set of utilities connecting EmonPi's ecosystem with CouchDB
Home-page: https://github.com/GeorgeVasiliadis/emon-utils
Author: George Vasiliadis
Author-email: geor.vasiliadis@gmail.com
License: MIT License
Platform: UNKNOWN
Classifier: Programming Language :: Python :: 3
Classifier: License :: OSI Approved :: MIT License
Classifier: Operating System :: OS Independent
Classifier: Topic :: Utilities
Classifier: Topic :: System :: Installation/Setup
Classifier: Topic :: Home Automation
Requires-Python: >=3.6
License-File: LICENSE
